computervisiontools/__init__.py
computervisiontools/preprocessing.py
computervisiontools/torchscripting.py
computervisiontools-0.1.0.dist-info/LICENSE.txt
computervisiontools-0.1.0.dist-info/METADATA
computervisiontools-0.1.0.dist-info/WHEEL
computervisiontools-0.1.0.dist-info/top_level.txt
computervisiontools-0.1.0.dist-info/RECORD
