Metadata-Version: 2.1
Name: computervisiontools
Version: 0.1.0
Summary: Overlay of PyTorch that contain utilities for basic task in computer vision (Image preprocessing, reading/writing images, set reproducibility, etc..).
Author-email: Lucas Bernigaud Samatan <lucas.bernigaud-samatan@inrae.fr>
Maintainer-email: Jordan Bernigaud Samatan <jordan.bernigaud-samatan@inrae.fr>
License: The MIT License (MIT)
Project-URL: Homepage, https://forgemia.inra.fr/ue-apc/librairies/python/detectools
Project-URL: Issues, https://forgemia.inra.fr/ue-apc/librairies/python/detectools/-/issues
Classifier: Development Status :: 3 - Alpha
Classifier: Programming Language :: Python :: 3
Classifier: Programming Language :: Python :: 3.10
Classifier: Programming Language :: Python :: 3.11
Requires-Python: >=3.10.12
License-File: LICENSE.txt
Requires-Dist: torch ==2.1.0
Requires-Dist: torchvision ==0.16.0
